[{"model": "auth.permission", "pk": 1, "fields": {"name": "Can add permission", "content_type": 1, "codename": "add_permission"}}, {"model": "auth.permission", "pk": 2, "fields": {"name": "Can change permission", "content_type": 1, "codename": "change_permission"}}, {"model": "auth.permission", "pk": 3, "fields": {"name": "Can delete permission", "content_type": 1, "codename": "delete_permission"}}, {"model": "auth.permission", "pk": 4, "fields": {"name": "Can view permission", "content_type": 1, "codename": "view_permission"}}, {"model": "auth.permission", "pk": 5, "fields": {"name": "Can add group", "content_type": 2, "codename": "add_group"}}, {"model": "auth.permission", "pk": 6, "fields": {"name": "Can change group", "content_type": 2, "codename": "change_group"}}, {"model": "auth.permission", "pk": 7, "fields": {"name": "Can delete group", "content_type": 2, "codename": "delete_group"}}, {"model": "auth.permission", "pk": 8, "fields": {"name": "Can view group", "content_type": 2, "codename": "view_group"}}, {"model": "auth.permission", "pk": 9, "fields": {"name": "Can add user", "content_type": 3, "codename": "add_user"}}, {"model": "auth.permission", "pk": 10, "fields": {"name": "Can change user", "content_type": 3, "codename": "change_user"}}, {"model": "auth.permission", "pk": 11, "fields": {"name": "Can delete user", "content_type": 3, "codename": "delete_user"}}, {"model": "auth.permission", "pk": 12, "fields": {"name": "Can view user", "content_type": 3, "codename": "view_user"}}, {"model": "auth.permission", "pk": 13, "fields": {"name": "Can add content type", "content_type": 4, "codename": "add_contenttype"}}, {"model": "auth.permission", "pk": 14, "fields": {"name": "Can change content type", "content_type": 4, "codename": "change_contenttype"}}, {"model": "auth.permission", "pk": 15, "fields": {"name": "Can delete content type", "content_type": 4, "codename": "delete_contenttype"}}, {"model": "auth.permission", "pk": 16, "fields": {"name": "Can view content type", "content_type": 4, "codename": "view_contenttype"}}, {"model": "auth.permission", "pk": 17, "fields": {"name": "Can add session", "content_type": 5, "codename": "add_session"}}, {"model": "auth.permission", "pk": 18, "fields": {"name": "Can change session", "content_type": 5, "codename": "change_session"}}, {"model": "auth.permission", "pk": 19, "fields": {"name": "Can delete session", "content_type": 5, "codename": "delete_session"}}, {"model": "auth.permission", "pk": 20, "fields": {"name": "Can view session", "content_type": 5, "codename": "view_session"}}, {"model": "auth.permission", "pk": 21, "fields": {"name": "Can add log entry", "content_type": 6, "codename": "add_logentry"}}, {"model": "auth.permission", "pk": 22, "fields": {"name": "Can change log entry", "content_type": 6, "codename": "change_logentry"}}, {"model": "auth.permission", "pk": 23, "fields": {"name": "Can delete log entry", "content_type": 6, "codename": "delete_logentry"}}, {"model": "auth.permission", "pk": 24, "fields": {"name": "Can view log entry", "content_type": 6, "codename": "view_logentry"}}, {"model": "auth.permission", "pk": 25, "fields": {"name": "Can add BaykeshopBrand", "content_type": 7, "codename": "add_baykeshopbrand"}}, {"model": "auth.permission", "pk": 26, "fields": {"name": "Can change BaykeshopBrand", "content_type": 7, "codename": "change_baykeshopbrand"}}, {"model": "auth.permission", "pk": 27, "fields": {"name": "Can delete BaykeshopBrand", "content_type": 7, "codename": "delete_baykeshopbrand"}}, {"model": "auth.permission", "pk": 28, "fields": {"name": "Can view BaykeshopBrand", "content_type": 7, "codename": "view_baykeshopbrand"}}, {"model": "auth.permission", "pk": 29, "fields": {"name": "Can add BaykeShopCategory", "content_type": 8, "codename": "add_baykeshopcategory"}}, {"model": "auth.permission", "pk": 30, "fields": {"name": "Can change BaykeShopCategory", "content_type": 8, "codename": "change_baykeshopcategory"}}, {"model": "auth.permission", "pk": 31, "fields": {"name": "Can delete BaykeShopCategory", "content_type": 8, "codename": "delete_baykeshopcategory"}}, {"model": "auth.permission", "pk": 32, "fields": {"name": "Can view BaykeShopCategory", "content_type": 8, "codename": "view_baykeshopcategory"}}, {"model": "auth.permission", "pk": 33, "fields": {"name": "Can add BaykeShopOrder", "content_type": 9, "codename": "add_baykeshoporder"}}, {"model": "auth.permission", "pk": 34, "fields": {"name": "Can change BaykeShopOrder", "content_type": 9, "codename": "change_baykeshoporder"}}, {"model": "auth.permission", "pk": 35, "fields": {"name": "Can delete BaykeShopOrder", "content_type": 9, "codename": "delete_baykeshoporder"}}, {"model": "auth.permission", "pk": 36, "fields": {"name": "Can view BaykeShopOrder", "content_type": 9, "codename": "view_baykeshoporder"}}, {"model": "auth.permission", "pk": 37, "fields": {"name": "Can add BaykeShopSpec", "content_type": 10, "codename": "add_baykeshopspec"}}, {"model": "auth.permission", "pk": 38, "fields": {"name": "Can change BaykeShopSpec", "content_type": 10, "codename": "change_baykeshopspec"}}, {"model": "auth.permission", "pk": 39, "fields": {"name": "Can delete BaykeShopSpec", "content_type": 10, "codename": "delete_baykeshopspec"}}, {"model": "auth.permission", "pk": 40, "fields": {"name": "Can view BaykeShopSpec", "content_type": 10, "codename": "view_baykeshopspec"}}, {"model": "auth.permission", "pk": 41, "fields": {"name": "Can add BaykeShopSPU", "content_type": 11, "codename": "add_baykeshopspu"}}, {"model": "auth.permission", "pk": 42, "fields": {"name": "Can change BaykeShopSPU", "content_type": 11, "codename": "change_baykeshopspu"}}, {"model": "auth.permission", "pk": 43, "fields": {"name": "Can delete BaykeShopSPU", "content_type": 11, "codename": "delete_baykeshopspu"}}, {"model": "auth.permission", "pk": 44, "fields": {"name": "Can view BaykeShopSPU", "content_type": 11, "codename": "view_baykeshopspu"}}, {"model": "auth.permission", "pk": 45, "fields": {"name": "Can add BaykeShopSpecValue", "content_type": 12, "codename": "add_baykeshopspecvalue"}}, {"model": "auth.permission", "pk": 46, "fields": {"name": "Can change BaykeShopSpecValue", "content_type": 12, "codename": "change_baykeshopspecvalue"}}, {"model": "auth.permission", "pk": 47, "fields": {"name": "Can delete BaykeShopSpecValue", "content_type": 12, "codename": "delete_baykeshopspecvalue"}}, {"model": "auth.permission", "pk": 48, "fields": {"name": "Can view BaykeShopSpecValue", "content_type": 12, "codename": "view_baykeshopspecvalue"}}, {"model": "auth.permission", "pk": 49, "fields": {"name": "Can add BaykeShopSKU", "content_type": 13, "codename": "add_baykeshopsku"}}, {"model": "auth.permission", "pk": 50, "fields": {"name": "Can change BaykeShopSKU", "content_type": 13, "codename": "change_baykeshopsku"}}, {"model": "auth.permission", "pk": 51, "fields": {"name": "Can delete BaykeShopSKU", "content_type": 13, "codename": "delete_baykeshopsku"}}, {"model": "auth.permission", "pk": 52, "fields": {"name": "Can view BaykeShopSKU", "content_type": 13, "codename": "view_baykeshopsku"}}, {"model": "auth.permission", "pk": 53, "fields": {"name": "Can add BaykeShopOrderSKU", "content_type": 14, "codename": "add_baykeshopordersku"}}, {"model": "auth.permission", "pk": 54, "fields": {"name": "Can change BaykeShopOrderSKU", "content_type": 14, "codename": "change_baykeshopordersku"}}, {"model": "auth.permission", "pk": 55, "fields": {"name": "Can delete BaykeShopOrderSKU", "content_type": 14, "codename": "delete_baykeshopordersku"}}, {"model": "auth.permission", "pk": 56, "fields": {"name": "Can view BaykeShopOrderSKU", "content_type": 14, "codename": "view_baykeshopordersku"}}, {"model": "auth.permission", "pk": 57, "fields": {"name": "Can add BaykeShopCart", "content_type": 15, "codename": "add_baykeshopcart"}}, {"model": "auth.permission", "pk": 58, "fields": {"name": "Can change BaykeShopCart", "content_type": 15, "codename": "change_baykeshopcart"}}, {"model": "auth.permission", "pk": 59, "fields": {"name": "Can delete BaykeShopCart", "content_type": 15, "codename": "delete_baykeshopcart"}}, {"model": "auth.permission", "pk": 60, "fields": {"name": "Can view BaykeShopCart", "content_type": 15, "codename": "view_baykeshopcart"}}, {"model": "auth.permission", "pk": 61, "fields": {"name": "Can add department", "content_type": 16, "codename": "add_baykedepartment"}}, {"model": "auth.permission", "pk": 62, "fields": {"name": "Can change department", "content_type": 16, "codename": "change_baykedepartment"}}, {"model": "auth.permission", "pk": 63, "fields": {"name": "Can delete department", "content_type": 16, "codename": "delete_baykedepartment"}}, {"model": "auth.permission", "pk": 64, "fields": {"name": "Can view department", "content_type": 16, "codename": "view_baykedepartment"}}, {"model": "auth.permission", "pk": 65, "fields": {"name": "Can add ByakeDictKey", "content_type": 17, "codename": "add_baykedictkey"}}, {"model": "auth.permission", "pk": 66, "fields": {"name": "Can change ByakeDictKey", "content_type": 17, "codename": "change_baykedictkey"}}, {"model": "auth.permission", "pk": 67, "fields": {"name": "Can delete ByakeDictKey", "content_type": 17, "codename": "delete_baykedictkey"}}, {"model": "auth.permission", "pk": 68, "fields": {"name": "Can view ByakeDictKey", "content_type": 17, "codename": "view_baykedictkey"}}, {"model": "auth.permission", "pk": 69, "fields": {"name": "Can add BaykeEmailConf", "content_type": 18, "codename": "add_baykeemailconf"}}, {"model": "auth.permission", "pk": 70, "fields": {"name": "Can change BaykeEmailConf", "content_type": 18, "codename": "change_baykeemailconf"}}, {"model": "auth.permission", "pk": 71, "fields": {"name": "Can delete BaykeEmailConf", "content_type": 18, "codename": "delete_baykeemailconf"}}, {"model": "auth.permission", "pk": 72, "fields": {"name": "Can view BaykeEmailConf", "content_type": 18, "codename": "view_baykeemailconf"}}, {"model": "auth.permission", "pk": 73, "fields": {"name": "Can add BaykeFrontedMenus", "content_type": 19, "codename": "add_baykefrontedmenus"}}, {"model": "auth.permission", "pk": 74, "fields": {"name": "Can change BaykeFrontedMenus", "content_type": 19, "codename": "change_baykefrontedmenus"}}, {"model": "auth.permission", "pk": 75, "fields": {"name": "Can delete BaykeFrontedMenus", "content_type": 19, "codename": "delete_baykefrontedmenus"}}, {"model": "auth.permission", "pk": 76, "fields": {"name": "Can view BaykeFrontedMenus", "content_type": 19, "codename": "view_baykefrontedmenus"}}, {"model": "auth.permission", "pk": 77, "fields": {"name": "Can add BaykeImage", "content_type": 20, "codename": "add_baykeimage"}}, {"model": "auth.permission", "pk": 78, "fields": {"name": "Can change BaykeImage", "content_type": 20, "codename": "change_baykeimage"}}, {"model": "auth.permission", "pk": 79, "fields": {"name": "Can delete BaykeImage", "content_type": 20, "codename": "delete_baykeimage"}}, {"model": "auth.permission", "pk": 80, "fields": {"name": "Can view BaykeImage", "content_type": 20, "codename": "view_baykeimage"}}, {"model": "auth.permission", "pk": 81, "fields": {"name": "Can add BaykeSystem", "content_type": 21, "codename": "add_baykesystem"}}, {"model": "auth.permission", "pk": 82, "fields": {"name": "Can change BaykeSystem", "content_type": 21, "codename": "change_baykesystem"}}, {"model": "auth.permission", "pk": 83, "fields": {"name": "Can delete BaykeSystem", "content_type": 21, "codename": "delete_baykesystem"}}, {"model": "auth.permission", "pk": 84, "fields": {"name": "Can view BaykeSystem", "content_type": 21, "codename": "view_baykesystem"}}, {"model": "auth.permission", "pk": 85, "fields": {"name": "Can add BaykeSystemExtend", "content_type": 22, "codename": "add_baykesystemextend"}}, {"model": "auth.permission", "pk": 86, "fields": {"name": "Can change BaykeSystemExtend", "content_type": 22, "codename": "change_baykesystemextend"}}, {"model": "auth.permission", "pk": 87, "fields": {"name": "Can delete BaykeSystemExtend", "content_type": 22, "codename": "delete_baykesystemextend"}}, {"model": "auth.permission", "pk": 88, "fields": {"name": "Can view BaykeSystemExtend", "content_type": 22, "codename": "view_baykesystemextend"}}, {"model": "auth.permission", "pk": 89, "fields": {"name": "Can add BaykeUser", "content_type": 23, "codename": "add_baykeuser"}}, {"model": "auth.permission", "pk": 90, "fields": {"name": "Can change BaykeUser", "content_type": 23, "codename": "change_baykeuser"}}, {"model": "auth.permission", "pk": 91, "fields": {"name": "用户删除", "content_type": 23, "codename": "delete_baykeuser"}}, {"model": "auth.permission", "pk": 92, "fields": {"name": "Can view BaykeUser", "content_type": 23, "codename": "view_baykeuser"}}, {"model": "auth.permission", "pk": 93, "fields": {"name": "Can add SiteMenus", "content_type": 24, "codename": "add_baykesitemenus"}}, {"model": "auth.permission", "pk": 94, "fields": {"name": "Can change SiteMenus", "content_type": 24, "codename": "change_baykesitemenus"}}, {"model": "auth.permission", "pk": 95, "fields": {"name": "Can delete SiteMenus", "content_type": 24, "codename": "delete_baykesitemenus"}}, {"model": "auth.permission", "pk": 96, "fields": {"name": "Can view SiteMenus", "content_type": 24, "codename": "view_baykesitemenus"}}, {"model": "auth.permission", "pk": 97, "fields": {"name": "Can add BaykeRoles", "content_type": 25, "codename": "add_baykeroles"}}, {"model": "auth.permission", "pk": 98, "fields": {"name": "Can change BaykeRoles", "content_type": 25, "codename": "change_baykeroles"}}, {"model": "auth.permission", "pk": 99, "fields": {"name": "Can delete BaykeRoles", "content_type": 25, "codename": "delete_baykeroles"}}, {"model": "auth.permission", "pk": 100, "fields": {"name": "Can view BaykeRoles", "content_type": 25, "codename": "view_baykeroles"}}, {"model": "auth.permission", "pk": 101, "fields": {"name": "Can add BaykePermissionAction", "content_type": 26, "codename": "add_baykepermissionaction"}}, {"model": "auth.permission", "pk": 102, "fields": {"name": "Can change BaykePermissionAction", "content_type": 26, "codename": "change_baykepermissionaction"}}, {"model": "auth.permission", "pk": 103, "fields": {"name": "Can delete BaykePermissionAction", "content_type": 26, "codename": "delete_baykepermissionaction"}}, {"model": "auth.permission", "pk": 104, "fields": {"name": "Can view BaykePermissionAction", "content_type": 26, "codename": "view_baykepermissionaction"}}, {"model": "auth.permission", "pk": 105, "fields": {"name": "Can add BaykeDictValue", "content_type": 27, "codename": "add_baykedictvalue"}}, {"model": "auth.permission", "pk": 106, "fields": {"name": "Can change BaykeDictValue", "content_type": 27, "codename": "change_baykedictvalue"}}, {"model": "auth.permission", "pk": 107, "fields": {"name": "Can delete BaykeDictValue", "content_type": 27, "codename": "delete_baykedictvalue"}}, {"model": "auth.permission", "pk": 108, "fields": {"name": "Can view BaykeDictValue", "content_type": 27, "codename": "view_baykedictvalue"}}, {"model": "auth.permission", "pk": 109, "fields": {"name": "Can add VerifyCode", "content_type": 28, "codename": "add_baykeverifycode"}}, {"model": "auth.permission", "pk": 110, "fields": {"name": "Can change VerifyCode", "content_type": 28, "codename": "change_baykeverifycode"}}, {"model": "auth.permission", "pk": 111, "fields": {"name": "Can delete VerifyCode", "content_type": 28, "codename": "delete_baykeverifycode"}}, {"model": "auth.permission", "pk": 112, "fields": {"name": "Can view VerifyCode", "content_type": 28, "codename": "view_baykeverifycode"}}, {"model": "auth.permission", "pk": 113, "fields": {"name": "Can add 余额明细", "content_type": 29, "codename": "add_baykeuserbalancelog"}}, {"model": "auth.permission", "pk": 114, "fields": {"name": "Can change 余额明细", "content_type": 29, "codename": "change_baykeuserbalancelog"}}, {"model": "auth.permission", "pk": 115, "fields": {"name": "Can delete 余额明细", "content_type": 29, "codename": "delete_baykeuserbalancelog"}}, {"model": "auth.permission", "pk": 116, "fields": {"name": "Can view 余额明细", "content_type": 29, "codename": "view_baykeuserbalancelog"}}, {"model": "auth.permission", "pk": 117, "fields": {"name": "Can add 收货地址", "content_type": 30, "codename": "add_baykeaddress"}}, {"model": "auth.permission", "pk": 118, "fields": {"name": "Can change 收货地址", "content_type": 30, "codename": "change_baykeaddress"}}, {"model": "auth.permission", "pk": 119, "fields": {"name": "Can delete 收货地址", "content_type": 30, "codename": "delete_baykeaddress"}}, {"model": "auth.permission", "pk": 120, "fields": {"name": "Can view 收货地址", "content_type": 30, "codename": "view_baykeaddress"}}, {"model": "auth.permission", "pk": 121, "fields": {"name": "Can add BaykeShopComment", "content_type": 31, "codename": "add_baykeshopcomment"}}, {"model": "auth.permission", "pk": 122, "fields": {"name": "Can change BaykeShopComment", "content_type": 31, "codename": "change_baykeshopcomment"}}, {"model": "auth.permission", "pk": 123, "fields": {"name": "Can delete BaykeShopComment", "content_type": 31, "codename": "delete_baykeshopcomment"}}, {"model": "auth.permission", "pk": 124, "fields": {"name": "Can view BaykeShopComment", "content_type": 31, "codename": "view_baykeshopcomment"}}, {"model": "auth.permission", "pk": 125, "fields": {"name": "Can add BaykeShopBanner", "content_type": 32, "codename": "add_baykeshopbanner"}}, {"model": "auth.permission", "pk": 126, "fields": {"name": "Can change BaykeShopBanner", "content_type": 32, "codename": "change_baykeshopbanner"}}, {"model": "auth.permission", "pk": 127, "fields": {"name": "Can delete BaykeShopBanner", "content_type": 32, "codename": "delete_baykeshopbanner"}}, {"model": "auth.permission", "pk": 128, "fields": {"name": "Can view BaykeShopBanner", "content_type": 32, "codename": "view_baykeshopbanner"}}, {"model": "auth.permission", "pk": 131, "fields": {"name": "新增商品分类", "content_type": 8, "codename": "create_shopcategory"}}, {"model": "auth.permission", "pk": 132, "fields": {"name": "修改商品分类", "content_type": 8, "codename": "update_shopcategory"}}, {"model": "auth.permission", "pk": 133, "fields": {"name": "局部修改商品分类", "content_type": 8, "codename": "patch_shopcategory"}}, {"model": "auth.permission", "pk": 134, "fields": {"name": "删除商品分类", "content_type": 8, "codename": "delete_shopcategory"}}, {"model": "auth.permission", "pk": 135, "fields": {"name": "批量删除商品分类", "content_type": 8, "codename": "batch_delete_shopcategory"}}, {"model": "auth.permission", "pk": 136, "fields": {"name": "商品分类列表", "content_type": 8, "codename": "list_shopcategory"}}, {"model": "auth.permission", "pk": 137, "fields": {"name": "部门新增", "content_type": 16, "codename": "create_badmindept"}}, {"model": "auth.permission", "pk": 138, "fields": {"name": "部门列表", "content_type": 16, "codename": "list_badmindept"}}, {"model": "auth.permission", "pk": 139, "fields": {"name": "部门删除", "content_type": 16, "codename": "delete_badmindept"}}, {"model": "auth.permission", "pk": 140, "fields": {"name": "部门批量删除", "content_type": 16, "codename": "batch_delete_badmindept"}}, {"model": "auth.permission", "pk": 141, "fields": {"name": "部门详情", "content_type": 16, "codename": "read_badmindept"}}, {"model": "auth.permission", "pk": 142, "fields": {"name": "部门修改", "content_type": 16, "codename": "update_badmindept"}}, {"model": "auth.permission", "pk": 143, "fields": {"name": "部门局部修改", "content_type": 16, "codename": "patch_badmindept"}}, {"model": "auth.permission", "pk": 144, "fields": {"name": "查看商品分类详情", "content_type": 8, "codename": "dead_shopcategory"}}, {"model": "auth.permission", "pk": 145, "fields": {"name": "角色新增", "content_type": 25, "codename": "create_badminroles"}}, {"model": "auth.permission", "pk": 146, "fields": {"name": "角色列表", "content_type": 25, "codename": "list_badminroles"}}, {"model": "auth.permission", "pk": 147, "fields": {"name": "角色详情", "content_type": 25, "codename": "read_badminroles"}}, {"model": "auth.permission", "pk": 148, "fields": {"name": "角色修改", "content_type": 25, "codename": "update_badminroles"}}, {"model": "auth.permission", "pk": 149, "fields": {"name": "角色局部修改", "content_type": 25, "codename": "patch_badminroles"}}, {"model": "auth.permission", "pk": 150, "fields": {"name": "角色删除", "content_type": 25, "codename": "delete_badminroles"}}, {"model": "auth.permission", "pk": 151, "fields": {"name": "角色批量删除", "content_type": 25, "codename": "batch_delete_badminroles"}}, {"model": "auth.permission", "pk": 152, "fields": {"name": "菜单列表", "content_type": 19, "codename": "list_badminmenus"}}, {"model": "auth.permission", "pk": 153, "fields": {"name": "菜单新增", "content_type": 19, "codename": "create_badminmenus"}}, {"model": "auth.permission", "pk": 154, "fields": {"name": "菜单详情", "content_type": 19, "codename": "read_badminmenus"}}, {"model": "auth.permission", "pk": 155, "fields": {"name": "菜单修改", "content_type": 19, "codename": "update_badminmenus"}}, {"model": "auth.permission", "pk": 156, "fields": {"name": "菜单局部修改", "content_type": 19, "codename": "patch_badminmenus"}}, {"model": "auth.permission", "pk": 157, "fields": {"name": "菜单删除", "content_type": 19, "codename": "delete_badminmenus"}}, {"model": "auth.permission", "pk": 158, "fields": {"name": "菜单批量删除", "content_type": 19, "codename": "batch_delete_badminmenus"}}, {"model": "auth.permission", "pk": 159, "fields": {"name": "接口新增", "content_type": 26, "codename": "create_badminaction"}}, {"model": "auth.permission", "pk": 160, "fields": {"name": "接口列表", "content_type": 26, "codename": "list_badminaction"}}, {"model": "auth.permission", "pk": 161, "fields": {"name": "接口详情", "content_type": 26, "codename": "read_badminaction"}}, {"model": "auth.permission", "pk": 162, "fields": {"name": "接口修改", "content_type": 26, "codename": "update_badminaction"}}, {"model": "auth.permission", "pk": 163, "fields": {"name": "接口局部修改", "content_type": 26, "codename": "patch_badminaction"}}, {"model": "auth.permission", "pk": 164, "fields": {"name": "接口删除", "content_type": 26, "codename": "delete_badminaction"}}, {"model": "auth.permission", "pk": 165, "fields": {"name": "接口批量删除", "content_type": 26, "codename": "batch_delete_badminaction"}}, {"model": "auth.permission", "pk": 166, "fields": {"name": "字典分类列表", "content_type": 17, "codename": "list_badmindictkey"}}, {"model": "auth.permission", "pk": 167, "fields": {"name": "字典分类新增", "content_type": 17, "codename": "create_badmindictkey"}}, {"model": "auth.permission", "pk": 168, "fields": {"name": "字典分类详情", "content_type": 17, "codename": "read_badmindictkey"}}, {"model": "auth.permission", "pk": 169, "fields": {"name": "字典分类修改", "content_type": 17, "codename": "update_badmindictkey"}}, {"model": "auth.permission", "pk": 170, "fields": {"name": "字典分类局部修改", "content_type": 17, "codename": "patch_badmindictkey"}}, {"model": "auth.permission", "pk": 171, "fields": {"name": "字典分类删除", "content_type": 17, "codename": "delete_badmindictkey"}}, {"model": "auth.permission", "pk": 172, "fields": {"name": "字典分类批量删除", "content_type": 17, "codename": "batch_delete_badmindictkey"}}, {"model": "auth.permission", "pk": 173, "fields": {"name": "字典新增", "content_type": 27, "codename": "create_badmindictvalue"}}, {"model": "auth.permission", "pk": 174, "fields": {"name": "字典列表", "content_type": 27, "codename": "list_badmindictvalue"}}, {"model": "auth.permission", "pk": 175, "fields": {"name": "字典详情", "content_type": 27, "codename": "read_badmindictvalue"}}, {"model": "auth.permission", "pk": 176, "fields": {"name": "字典修改", "content_type": 27, "codename": "update_badmindictvalue"}}, {"model": "auth.permission", "pk": 177, "fields": {"name": "字典局部修改", "content_type": 27, "codename": "patch_badmindictvalue"}}, {"model": "auth.permission", "pk": 178, "fields": {"name": "字典删除", "content_type": 27, "codename": "delete_badmindictvalue"}}, {"model": "auth.permission", "pk": 179, "fields": {"name": "字典批量删除", "content_type": 27, "codename": "batch_delete_badmindictvalue"}}, {"model": "auth.permission", "pk": 180, "fields": {"name": "用户列表", "content_type": 23, "codename": "list_baykeuser"}}, {"model": "auth.permission", "pk": 181, "fields": {"name": "用户详情", "content_type": 23, "codename": "read_baykeuser"}}, {"model": "auth.permission", "pk": 182, "fields": {"name": "用户新增", "content_type": 23, "codename": "create_baykeuser"}}, {"model": "auth.permission", "pk": 183, "fields": {"name": "用户修改", "content_type": 23, "codename": "update_baykeuser"}}, {"model": "auth.permission", "pk": 184, "fields": {"name": "用户局部修改", "content_type": 23, "codename": "patch_baykeuser"}}, {"model": "auth.permission", "pk": 185, "fields": {"name": "用户批量删除", "content_type": 23, "codename": "batch_delete_baykeuser"}}, {"model": "auth.permission", "pk": 186, "fields": {"name": "系统配置详情", "content_type": 21, "codename": "read_system"}}, {"model": "auth.permission", "pk": 187, "fields": {"name": "系统配置修改", "content_type": 21, "codename": "update_system"}}, {"model": "auth.permission", "pk": 188, "fields": {"name": "系统配置局部修改", "content_type": 21, "codename": "patch_system"}}, {"model": "auth.permission", "pk": 189, "fields": {"name": "邮箱配置详情", "content_type": 18, "codename": "read_emailconf"}}, {"model": "auth.permission", "pk": 190, "fields": {"name": "邮箱配置修改", "content_type": 18, "codename": "update_emailconf"}}, {"model": "auth.permission", "pk": 191, "fields": {"name": "邮箱配置局部修改", "content_type": 18, "codename": "patch_emailconf"}}, {"model": "auth.permission", "pk": 192, "fields": {"name": "站点扩展配置列表", "content_type": 22, "codename": "list_system_extend"}}, {"model": "auth.permission", "pk": 193, "fields": {"name": "站点扩展配置新增", "content_type": 22, "codename": "create_system_extend"}}, {"model": "auth.permission", "pk": 194, "fields": {"name": "站点扩展配置详情", "content_type": 22, "codename": "read_system_extend"}}, {"model": "auth.permission", "pk": 195, "fields": {"name": "站点扩展配置修改", "content_type": 22, "codename": "update_system_extend"}}, {"model": "auth.permission", "pk": 196, "fields": {"name": "站点扩展配置局部修改", "content_type": 22, "codename": "patch_system_extend"}}, {"model": "auth.permission", "pk": 197, "fields": {"name": "站点扩展配置删除", "content_type": 22, "codename": "delete_system_extend"}}, {"model": "auth.permission", "pk": 198, "fields": {"name": "站点扩展配置批量删除", "content_type": 22, "codename": "batch_delete_system_extend"}}, {"model": "auth.permission", "pk": 199, "fields": {"name": "商品品牌列表", "content_type": 7, "codename": "list_brand"}}, {"model": "auth.permission", "pk": 200, "fields": {"name": "商品品牌详情", "content_type": 7, "codename": "read_brand"}}, {"model": "auth.permission", "pk": 201, "fields": {"name": "商品品牌新增", "content_type": 7, "codename": "create_brand"}}, {"model": "auth.permission", "pk": 202, "fields": {"name": "商品品牌修改", "content_type": 7, "codename": "update_brand"}}, {"model": "auth.permission", "pk": 203, "fields": {"name": "商品品牌局部修改", "content_type": 7, "codename": "patch_brand"}}, {"model": "auth.permission", "pk": 204, "fields": {"name": "商品品牌删除", "content_type": 7, "codename": "delete_brand"}}, {"model": "auth.permission", "pk": 205, "fields": {"name": "商品品牌批量删除", "content_type": 7, "codename": "batch_delete_brand"}}, {"model": "auth.permission", "pk": 206, "fields": {"name": "商品SPU列表", "content_type": 11, "codename": "list_spu"}}, {"model": "auth.permission", "pk": 207, "fields": {"name": "商品SPU新增", "content_type": 11, "codename": "create_spu"}}, {"model": "auth.permission", "pk": 208, "fields": {"name": "商品SPU详情", "content_type": 11, "codename": "read_spu"}}, {"model": "auth.permission", "pk": 209, "fields": {"name": "商品SPU修改", "content_type": 11, "codename": "update_spu"}}, {"model": "auth.permission", "pk": 210, "fields": {"name": "商品SPU局部修改", "content_type": 11, "codename": "patch_spu"}}, {"model": "auth.permission", "pk": 211, "fields": {"name": "商品SPU删除", "content_type": 11, "codename": "delete_spu"}}, {"model": "auth.permission", "pk": 212, "fields": {"name": "商品SPU批量删除", "content_type": 11, "codename": "batch_delete_spu"}}, {"model": "auth.permission", "pk": 213, "fields": {"name": "商品SKU列表", "content_type": 13, "codename": "list_sku"}}, {"model": "auth.permission", "pk": 214, "fields": {"name": "商品SKU详情", "content_type": 13, "codename": "read_sku"}}, {"model": "auth.permission", "pk": 215, "fields": {"name": "商品SKU删除", "content_type": 13, "codename": "delete_sku"}}, {"model": "auth.permission", "pk": 216, "fields": {"name": "商品SKU批量删除", "content_type": 13, "codename": "batch_delete_sku"}}, {"model": "auth.permission", "pk": 217, "fields": {"name": "商品规格列表", "content_type": 10, "codename": "list_spec"}}, {"model": "auth.permission", "pk": 218, "fields": {"name": "商品规格新增", "content_type": 10, "codename": "create_spec"}}, {"model": "auth.permission", "pk": 219, "fields": {"name": "商品规格详情", "content_type": 10, "codename": "read_spec"}}, {"model": "auth.permission", "pk": 220, "fields": {"name": "商品规格删除", "content_type": 10, "codename": "delete_spec"}}, {"model": "auth.permission", "pk": 221, "fields": {"name": "商品规格修改", "content_type": 10, "codename": "update_spec"}}, {"model": "auth.permission", "pk": 222, "fields": {"name": "商品规格局部修改", "content_type": 10, "codename": "patch_spec"}}, {"model": "auth.permission", "pk": 223, "fields": {"name": "商品规格批量删除", "content_type": 10, "codename": "batch_delete_spec"}}, {"model": "auth.permission", "pk": 224, "fields": {"name": "商品规格值列表", "content_type": 12, "codename": "list_specvalue"}}, {"model": "auth.permission", "pk": 225, "fields": {"name": "商品规格值新增", "content_type": 12, "codename": "create_specvalue"}}, {"model": "auth.permission", "pk": 226, "fields": {"name": "商品规格值详情", "content_type": 12, "codename": "read_specvalue"}}, {"model": "auth.permission", "pk": 227, "fields": {"name": "商品规格值修改", "content_type": 12, "codename": "update_specvalue"}}, {"model": "auth.permission", "pk": 228, "fields": {"name": "商品规格值局部修改", "content_type": 12, "codename": "patch_specvalue"}}, {"model": "auth.permission", "pk": 229, "fields": {"name": "商品规格值删除", "content_type": 12, "codename": "delete_specvalue"}}, {"model": "auth.permission", "pk": 230, "fields": {"name": "商品规格值批量删除", "content_type": 12, "codename": "batch_delete_specvalue"}}, {"model": "auth.permission", "pk": 231, "fields": {"name": "轮播图新增", "content_type": 32, "codename": "create_banner"}}, {"model": "auth.permission", "pk": 232, "fields": {"name": "轮播图修改", "content_type": 32, "codename": "update_banner"}}, {"model": "auth.permission", "pk": 233, "fields": {"name": "轮播图局部修改", "content_type": 32, "codename": "patch_banner"}}, {"model": "auth.permission", "pk": 234, "fields": {"name": "轮播图删除", "content_type": 32, "codename": "delete_banner"}}, {"model": "auth.permission", "pk": 235, "fields": {"name": "轮播图批量删除", "content_type": 32, "codename": "batch_delete_banner"}}, {"model": "auth.permission", "pk": 236, "fields": {"name": "商品评论列表", "content_type": 31, "codename": "list_comment"}}, {"model": "auth.permission", "pk": 237, "fields": {"name": "商品评论回复", "content_type": 31, "codename": "update_comment"}}, {"model": "auth.permission", "pk": 238, "fields": {"name": "商品评论局部回复", "content_type": 31, "codename": "patch_comment"}}, {"model": "auth.permission", "pk": 239, "fields": {"name": "商品评论删除", "content_type": 31, "codename": "delete_comment"}}, {"model": "auth.permission", "pk": 240, "fields": {"name": "商品评论批量删除", "content_type": 31, "codename": "batch_delete_comment"}}, {"model": "auth.permission", "pk": 241, "fields": {"name": "订单列表", "content_type": 9, "codename": "list_order"}}, {"model": "auth.permission", "pk": 242, "fields": {"name": "订单详情", "content_type": 9, "codename": "read_order"}}, {"model": "auth.permission", "pk": 243, "fields": {"name": "订单修改", "content_type": 9, "codename": "update_order"}}, {"model": "auth.permission", "pk": 244, "fields": {"name": "订单局部修改", "content_type": 9, "codename": "patch_order"}}, {"model": "auth.permission", "pk": 245, "fields": {"name": "订单删除", "content_type": 9, "codename": "delete_order"}}, {"model": "auth.permission", "pk": 246, "fields": {"name": "订单批量删除", "content_type": 9, "codename": "batch_delete_order"}}, {"model": "auth.permission", "pk": 247, "fields": {"name": "应用列表", "content_type": 4, "codename": "list_content_type"}}]